scripts/__init__.py
scripts/attention.py
scripts/parsers.py
scripts/sample.py
scripts/train.py
transvae/__init__.py
transvae/analysis.py
transvae/data.py
transvae/loss.py
transvae/opt.py
transvae/rnn_models.py
transvae/trans_models.py
transvae/tvae_util.py
transvae/version.py
transvae-0.6.1.dist-info/LICENSE
transvae-0.6.1.dist-info/METADATA
transvae-0.6.1.dist-info/WHEEL
transvae-0.6.1.dist-info/top_level.txt
transvae-0.6.1.dist-info/RECORD
