Metadata-Version: 2.1
Name: transvae
Version: 0.6.1
Summary: A package for training and analyzing attention-based VAEs for molecular design.
Home-page: https://github.com/oriondollar/TransVAE
Author: Orion Dollar
Author-email: orion.dollar@gmail.com
Maintainer: Orion Dollar
Maintainer-email: orion.dollar@gmail.com
License: MIT License
Platform: OS Independent
Classifier: Intended Audience :: Science/Research
Classifier: License :: OSI Approved :: MIT License
Classifier: Operating System :: OS Independent
Classifier: Programming Language :: Python
Classifier: Topic :: Scientific/Engineering
License-File: LICENSE
Requires-Dist: pandas
Requires-Dist: numpy
Requires-Dist: torch
Requires-Dist: seaborn
Requires-Dist: matplotlib
Requires-Dist: scipy
Requires-Dist: sklearn
